claudette/__init__.py
claudette/_modidx.py
claudette/asink.py
claudette/core.py
claudette/text_editor.py
claudette/toolloop.py
claudette-0.3.10.dist-info/licenses/LICENSE
claudette-0.3.10.dist-info/METADATA
claudette-0.3.10.dist-info/WHEEL
claudette-0.3.10.dist-info/entry_points.txt
claudette-0.3.10.dist-info/top_level.txt
claudette-0.3.10.dist-info/RECORD
