Metadata-Version: 2.4
Name: claudette
Version: 0.3.10
Summary: Claudette is Claude's friend
Home-page: https://github.com/AnswerDotAI/claudette
Author: Jeremy Howard
Author-email: j@fast.ai
License: Apache Software License 2.0
Keywords: nbdev jupyter notebook python
Classifier: Development Status :: 5 - Production/Stable
Classifier: Intended Audience :: Developers
Classifier: Natural Language :: English
Classifier: Programming Language :: Python :: 3.9
Classifier: Programming Language :: Python :: 3.10
Classifier: License :: OSI Approved :: Apache Software License
Requires-Python: >=3.9
License-File: LICENSE
Requires-Dist: fastcore>=1.8.4
Requires-Dist: msglm>=0.0.9
Requires-Dist: anthropic>=0.52
Requires-Dist: toolslm>=0.3.0
Provides-Extra: dev
Requires-Dist: google-auth; extra == "dev"
Requires-Dist: pycachy; extra == "dev"
Dynamic: author
Dynamic: author-email
Dynamic: classifier
Dynamic: description
Dynamic: description-content-type
Dynamic: home-page
Dynamic: keywords
Dynamic: license
Dynamic: license-file
Dynamic: provides-extra
Dynamic: requires-dist
Dynamic: requires-python
Dynamic: summary
